text_game_map_maker/__init__.py
text_game_map_maker/__main__.py
text_game_map_maker/constants.py
text_game_map_maker/door_editor.py
text_game_map_maker/forms.py
text_game_map_maker/git_rev.py
text_game_map_maker/map_editor.py
text_game_map_maker/object_browsers.py
text_game_map_maker/object_builders.py
text_game_map_maker/qt_auto_form.py
text_game_map_maker/saved_objects.py
text_game_map_maker/scrollarea.py
text_game_map_maker/tgmdata.py
text_game_map_maker/tile_button.py
text_game_map_maker/utils.py
text_game_map_maker/images/compass.png
text_game_map_maker/images/logo.png
text_game_map_maker-0.1.9.dist-info/DESCRIPTION.rst
text_game_map_maker-0.1.9.dist-info/METADATA
text_game_map_maker-0.1.9.dist-info/RECORD
text_game_map_maker-0.1.9.dist-info/WHEEL
text_game_map_maker-0.1.9.dist-info/metadata.json
text_game_map_maker-0.1.9.dist-info/top_level.txt
