Metadata-Version: 2.0
Name: text-game-map-maker
Version: 0.1.9
Summary: Graphical tool for building maps to be used with text_game_maker
Home-page: http://github.com/eriknyquist/text_game_map_maker
Author: Erik Nyquist
Author-email: eknyquist@gmail.com
License: Apache 2.0
Platform: UNKNOWN
Requires-Dist: pyqt5
Requires-Dist: text-game-maker (==0.7.5)
